{"site_data":{"project_name":"mini-hott","files_count":172,"authors":[{"commits":23,"name":"Jonathan Prieto-Cubides","email":"jcu043@uib.no"}],"total_commits":23,"total_additions":297256,"total_subtractions":113974,"first_commit":{"short_sha":"0a0619d","long_sha":"0a0619d64ab5ec52dd9b3f7cf99a4728f7567109","author_name":"Jonathan Prieto-Cubides","author_email":"jcu043@uib.no","author_date":"Sat Apr 6 13:27:07 2019 +0200","commit_date":"Sat Apr 6 13:27:07 2019 +0200","message":"Added .gitignore file"},"last_commit":{"short_sha":"3dbb591","long_sha":"3dbb591bcec8224b2400f3ba4b247c448c8a9c5d","author_name":"Jonathan Prieto-Cubides","author_email":"jcu043@uib.no","author_date":"Thu Jun 20 17:24:21 2019 +0200","commit_date":"Thu Jun 20 17:24:21 2019 +0200","message":"Add more theorems"}},"pages_data":{"404.html":{"authors":[{"commits":1,"name":"Jonathan Prieto-Cubides","email":"jcu043@uib.no"}],"total_commits":1,"total_additions":9,"total_subtractions":0,"first_commit":{"short_sha":"51a0ec7","long_sha":"51a0ec7cc21422c39e9bc138691d9f9726746854","author_name":"Jonathan Prieto-Cubides","author_email":"jcu043@uib.no","author_date":"Mon Apr 8 18:40:13 2019 +0200","commit_date":"Mon Apr 8 18:40:13 2019 +0200","message":"Fixing html generations for jekyll"},"last_commit":{"short_sha":"51a0ec7","long_sha":"51a0ec7cc21422c39e9bc138691d9f9726746854","author_name":"Jonathan Prieto-Cubides","author_email":"jcu043@uib.no","author_date":"Mon Apr 8 18:40:13 2019 +0200","commit_date":"Mon Apr 8 18:40:13 2019 +0200","message":"Fixing html generations for jekyll"}},"AlgebraOnPaths.md":{"authors":[{"commits":4,"name":"Jonathan Prieto-Cubides","email":"jcu043@uib.no"}],"total_commits":4,"total_additions":920,"total_subtractions":570,"first_commit":{"short_sha":"1da8e9a","long_sha":"1da8e9a76da455368ce8e88f938d457428dcc0b4","author_name":"Jonathan Prieto-Cubides","author_email":"jcu043@uib.no","author_date":"Mon Apr 8 21:58:48 2019 +0200","commit_date":"Mon Apr 8 21:58:48 2019 +0200","message":"Fixed targets for Makefile"},"last_commit":{"short_sha":"3dbb591","long_sha":"3dbb591bcec8224b2400f3ba4b247c448c8a9c5d","author_name":"Jonathan Prieto-Cubides","author_email":"jcu043@uib.no","author_date":"Thu Jun 20 17:24:21 2019 +0200","commit_date":"Thu Jun 20 17:24:21 2019 +0200","message":"Add more theorems"}},"AlgebraOnPaths.tex":{"authors":[{"commits":3,"name":"Jonathan Prieto-Cubides","email":"jcu043@uib.no"}],"total_commits":3,"total_additions":734,"total_subtractions":384,"first_commit":{"short_sha":"bddced8","long_sha":"bddced8b62924abdef08b8978500b0b1e124c58e","author_name":"Jonathan Prieto-Cubides","author_email":"jcu043@uib.no","author_date":"Tue Apr 30 12:24:41 2019 +0200","commit_date":"Tue Apr 30 12:24:41 2019 +0200","message":"Added some lemmas about propositions"},"last_commit":{"short_sha":"3dbb591","long_sha":"3dbb591bcec8224b2400f3ba4b247c448c8a9c5d","author_name":"Jonathan Prieto-Cubides","author_email":"jcu043@uib.no","author_date":"Thu Jun 20 17:24:21 2019 +0200","commit_date":"Thu Jun 20 17:24:21 2019 +0200","message":"Add more theorems"}},"BasicFunctions.md":{"authors":[{"commits":3,"name":"Jonathan Prieto-Cubides","email":"jcu043@uib.no"}],"total_commits":3,"total_additions":578,"total_subtractions":226,"first_commit":{"short_sha":"1da8e9a","long_sha":"1da8e9a76da455368ce8e88f938d457428dcc0b4","author_name":"Jonathan Prieto-Cubides","author_email":"jcu043@uib.no","author_date":"Mon Apr 8 21:58:48 2019 +0200","commit_date":"Mon Apr 8 21:58:48 2019 +0200","message":"Fixed targets for Makefile"},"last_commit":{"short_sha":"3dbb591","long_sha":"3dbb591bcec8224b2400f3ba4b247c448c8a9c5d","author_name":"Jonathan Prieto-Cubides","author_email":"jcu043@uib.no","author_date":"Thu Jun 20 17:24:21 2019 +0200","commit_date":"Thu Jun 20 17:24:21 2019 +0200","message":"Add more theorems"}},"BasicFunctions.tex":null,"BasicTypes.md":{"authors":[{"commits":4,"name":"Jonathan Prieto-Cubides","email":"jcu043@uib.no"}],"total_commits":4,"total_additions":631,"total_subtractions":260,"first_commit":{"short_sha":"1da8e9a","long_sha":"1da8e9a76da455368ce8e88f938d457428dcc0b4","author_name":"Jonathan Prieto-Cubides","author_email":"jcu043@uib.no","author_date":"Mon Apr 8 21:58:48 2019 +0200","commit_date":"Mon Apr 8 21:58:48 2019 +0200","message":"Fixed targets for Makefile"},"last_commit":{"short_sha":"3dbb591","long_sha":"3dbb591bcec8224b2400f3ba4b247c448c8a9c5d","author_name":"Jonathan Prieto-Cubides","author_email":"jcu043@uib.no","author_date":"Thu Jun 20 17:24:21 2019 +0200","commit_date":"Thu Jun 20 17:24:21 2019 +0200","message":"Add more theorems"}},"BasicTypes.tex":{"authors":[{"commits":4,"name":"Jonathan Prieto-Cubides","email":"jcu043@uib.no"}],"total_commits":4,"total_additions":631,"total_subtractions":260,"first_commit":{"short_sha":"990a4d7","long_sha":"990a4d74b64e5655a7fbef358b8a03ff31fee727","author_name":"Jonathan Prieto-Cubides","author_email":"jcu043@uib.no","author_date":"Tue Apr 16 21:12:49 2019 +0100","commit_date":"Tue Apr 16 21:12:49 2019 +0100","message":"Fixing link raw agda/edit/history"},"last_commit":{"short_sha":"3dbb591","long_sha":"3dbb591bcec8224b2400f3ba4b247c448c8a9c5d","author_name":"Jonathan Prieto-Cubides","author_email":"jcu043@uib.no","author_date":"Thu Jun 20 17:24:21 2019 +0200","commit_date":"Thu Jun 20 17:24:21 2019 +0200","message":"Add more theorems"}},"CircleType.md":{"authors":[{"commits":3,"name":"Jonathan Prieto-Cubides","email":"jcu043@uib.no"}],"total_commits":3,"total_additions":93,"total_subtractions":14,"first_commit":{"short_sha":"1da8e9a","long_sha":"1da8e9a76da455368ce8e88f938d457428dcc0b4","author_name":"Jonathan Prieto-Cubides","author_email":"jcu043@uib.no","author_date":"Mon Apr 8 21:58:48 2019 +0200","commit_date":"Mon Apr 8 21:58:48 2019 +0200","message":"Fixed targets for Makefile"},"last_commit":{"short_sha":"e5ca005","long_sha":"e5ca0055367c20b9201e4ff56af1db0d5a7153e3","author_name":"Jonathan Prieto-Cubides","author_email":"jcu043@uib.no","author_date":"Thu Jun 20 03:17:26 2019 +0200","commit_date":"Thu Jun 20 03:17:26 2019 +0200","message":"Tons of additions."}},"CircleType.tex":{"authors":[{"commits":3,"name":"Jonathan Prieto-Cubides","email":"jcu043@uib.no"}],"total_commits":3,"total_additions":105,"total_subtractions":26,"first_commit":{"short_sha":"bddced8","long_sha":"bddced8b62924abdef08b8978500b0b1e124c58e","author_name":"Jonathan Prieto-Cubides","author_email":"jcu043@uib.no","author_date":"Tue Apr 30 12:24:41 2019 +0200","commit_date":"Tue Apr 30 12:24:41 2019 +0200","message":"Added some lemmas about propositions"},"last_commit":{"short_sha":"3dbb591","long_sha":"3dbb591bcec8224b2400f3ba4b247c448c8a9c5d","author_name":"Jonathan Prieto-Cubides","author_email":"jcu043@uib.no","author_date":"Thu Jun 20 17:24:21 2019 +0200","commit_date":"Thu Jun 20 17:24:21 2019 +0200","message":"Add more theorems"}},"ContractibleType.md":{"authors":[{"commits":3,"name":"Jonathan Prieto-Cubides","email":"jcu043@uib.no"}],"total_commits":3,"total_additions":97,"total_subtractions":29,"first_commit":{"short_sha":"1da8e9a","long_sha":"1da8e9a76da455368ce8e88f938d457428dcc0b4","author_name":"Jonathan Prieto-Cubides","author_email":"jcu043@uib.no","author_date":"Mon Apr 8 21:58:48 2019 +0200","commit_date":"Mon Apr 8 21:58:48 2019 +0200","message":"Fixed targets for Makefile"},"last_commit":{"short_sha":"e5ca005","long_sha":"e5ca0055367c20b9201e4ff56af1db0d5a7153e3","author_name":"Jonathan Prieto-Cubides","author_email":"jcu043@uib.no","author_date":"Thu Jun 20 03:17:26 2019 +0200","commit_date":"Thu Jun 20 03:17:26 2019 +0200","message":"Tons of additions."}},"ContractibleType.tex":{"authors":[{"commits":3,"name":"Jonathan Prieto-Cubides","email":"jcu043@uib.no"}],"total_commits":3,"total_additions":97,"total_subtractions":29,"first_commit":{"short_sha":"bddced8","long_sha":"bddced8b62924abdef08b8978500b0b1e124c58e","author_name":"Jonathan Prieto-Cubides","author_email":"jcu043@uib.no","author_date":"Tue Apr 30 12:24:41 2019 +0200","commit_date":"Tue Apr 30 12:24:41 2019 +0200","message":"Added some lemmas about propositions"},"last_commit":{"short_sha":"e5ca005","long_sha":"e5ca0055367c20b9201e4ff56af1db0d5a7153e3","author_name":"Jonathan Prieto-Cubides","author_email":"jcu043@uib.no","author_date":"Thu Jun 20 03:17:26 2019 +0200","commit_date":"Thu Jun 20 03:17:26 2019 +0200","message":"Tons of additions."}},"CoproductIdentities.md":{"authors":[{"commits":2,"name":"Jonathan Prieto-Cubides","email":"jcu043@uib.no"}],"total_commits":2,"total_additions":268,"total_subtractions":81,"first_commit":{"short_sha":"e5ca005","long_sha":"e5ca0055367c20b9201e4ff56af1db0d5a7153e3","author_name":"Jonathan Prieto-Cubides","author_email":"jcu043@uib.no","author_date":"Thu Jun 20 03:17:26 2019 +0200","commit_date":"Thu Jun 20 03:17:26 2019 +0200","message":"Tons of additions."},"last_commit":{"short_sha":"3dbb591","long_sha":"3dbb591bcec8224b2400f3ba4b247c448c8a9c5d","author_name":"Jonathan Prieto-Cubides","author_email":"jcu043@uib.no","author_date":"Thu Jun 20 17:24:21 2019 +0200","commit_date":"Thu Jun 20 17:24:21 2019 +0200","message":"Add more theorems"}},"CoproductIdentities.tex":null,"DecidableEquality.md":{"authors":[{"commits":4,"name":"Jonathan Prieto-Cubides","email":"jcu043@uib.no"}],"total_commits":4,"total_additions":77,"total_subtractions":24,"first_commit":{"short_sha":"1da8e9a","long_sha":"1da8e9a76da455368ce8e88f938d457428dcc0b4","author_name":"Jonathan Prieto-Cubides","author_email":"jcu043@uib.no","author_date":"Mon Apr 8 21:58:48 2019 +0200","commit_date":"Mon Apr 8 21:58:48 2019 +0200","message":"Fixed targets for Makefile"},"last_commit":{"short_sha":"e5ca005","long_sha":"e5ca0055367c20b9201e4ff56af1db0d5a7153e3","author_name":"Jonathan Prieto-Cubides","author_email":"jcu043@uib.no","author_date":"Thu Jun 20 03:17:26 2019 +0200","commit_date":"Thu Jun 20 03:17:26 2019 +0200","message":"Tons of additions."}},"DecidableEquality.tex":{"authors":[{"commits":5,"name":"Jonathan Prieto-Cubides","email":"jcu043@uib.no"}],"total_commits":5,"total_additions":84,"total_subtractions":31,"first_commit":{"short_sha":"bddced8","long_sha":"bddced8b62924abdef08b8978500b0b1e124c58e","author_name":"Jonathan Prieto-Cubides","author_email":"jcu043@uib.no","author_date":"Tue Apr 30 12:24:41 2019 +0200","commit_date":"Tue Apr 30 12:24:41 2019 +0200","message":"Added some lemmas about propositions"},"last_commit":{"short_sha":"3dbb591","long_sha":"3dbb591bcec8224b2400f3ba4b247c448c8a9c5d","author_name":"Jonathan Prieto-Cubides","author_email":"jcu043@uib.no","author_date":"Thu Jun 20 17:24:21 2019 +0200","commit_date":"Thu Jun 20 17:24:21 2019 +0200","message":"Add more theorems"}},"EqualityType.md":{"authors":[{"commits":2,"name":"Jonathan Prieto-Cubides","email":"jcu043@uib.no"}],"total_commits":2,"total_additions":385,"total_subtractions":114,"first_commit":{"short_sha":"1da8e9a","long_sha":"1da8e9a76da455368ce8e88f938d457428dcc0b4","author_name":"Jonathan Prieto-Cubides","author_email":"jcu043@uib.no","author_date":"Mon Apr 8 21:58:48 2019 +0200","commit_date":"Mon Apr 8 21:58:48 2019 +0200","message":"Fixed targets for Makefile"},"last_commit":{"short_sha":"e5ca005","long_sha":"e5ca0055367c20b9201e4ff56af1db0d5a7153e3","author_name":"Jonathan Prieto-Cubides","author_email":"jcu043@uib.no","author_date":"Thu Jun 20 03:17:26 2019 +0200","commit_date":"Thu Jun 20 03:17:26 2019 +0200","message":"Tons of additions."}},"EqualityType.tex":{"authors":[{"commits":2,"name":"Jonathan Prieto-Cubides","email":"jcu043@uib.no"}],"total_commits":2,"total_additions":385,"total_subtractions":114,"first_commit":{"short_sha":"bddced8","long_sha":"bddced8b62924abdef08b8978500b0b1e124c58e","author_name":"Jonathan Prieto-Cubides","author_email":"jcu043@uib.no","author_date":"Tue Apr 30 12:24:41 2019 +0200","commit_date":"Tue Apr 30 12:24:41 2019 +0200","message":"Added some lemmas about propositions"},"last_commit":{"short_sha":"e5ca005","long_sha":"e5ca0055367c20b9201e4ff56af1db0d5a7153e3","author_name":"Jonathan Prieto-Cubides","author_email":"jcu043@uib.no","author_date":"Thu Jun 20 03:17:26 2019 +0200","commit_date":"Thu Jun 20 03:17:26 2019 +0200","message":"Tons of additions."}},"EquivalenceReasoning.md":{"authors":[{"commits":2,"name":"Jonathan Prieto-Cubides","email":"jcu043@uib.no"}],"total_commits":2,"total_additions":76,"total_subtractions":14,"first_commit":{"short_sha":"1da8e9a","long_sha":"1da8e9a76da455368ce8e88f938d457428dcc0b4","author_name":"Jonathan Prieto-Cubides","author_email":"jcu043@uib.no","author_date":"Mon Apr 8 21:58:48 2019 +0200","commit_date":"Mon Apr 8 21:58:48 2019 +0200","message":"Fixed targets for Makefile"},"last_commit":{"short_sha":"e5ca005","long_sha":"e5ca0055367c20b9201e4ff56af1db0d5a7153e3","author_name":"Jonathan Prieto-Cubides","author_email":"jcu043@uib.no","author_date":"Thu Jun 20 03:17:26 2019 +0200","commit_date":"Thu Jun 20 03:17:26 2019 +0200","message":"Tons of additions."}},"EquivalenceReasoning.tex":{"authors":[{"commits":3,"name":"Jonathan Prieto-Cubides","email":"jcu043@uib.no"}],"total_commits":3,"total_additions":85,"total_subtractions":23,"first_commit":{"short_sha":"bddced8","long_sha":"bddced8b62924abdef08b8978500b0b1e124c58e","author_name":"Jonathan Prieto-Cubides","author_email":"jcu043@uib.no","author_date":"Tue Apr 30 12:24:41 2019 +0200","commit_date":"Tue Apr 30 12:24:41 2019 +0200","message":"Added some lemmas about propositions"},"last_commit":{"short_sha":"3dbb591","long_sha":"3dbb591bcec8224b2400f3ba4b247c448c8a9c5d","author_name":"Jonathan Prieto-Cubides","author_email":"jcu043@uib.no","author_date":"Thu Jun 20 17:24:21 2019 +0200","commit_date":"Thu Jun 20 17:24:21 2019 +0200","message":"Add more theorems"}},"EquivalenceType.md":{"authors":[{"commits":5,"name":"Jonathan Prieto-Cubides","email":"jcu043@uib.no"}],"total_commits":5,"total_additions":337,"total_subtractions":199,"first_commit":{"short_sha":"1da8e9a","long_sha":"1da8e9a76da455368ce8e88f938d457428dcc0b4","author_name":"Jonathan Prieto-Cubides","author_email":"jcu043@uib.no","author_date":"Mon Apr 8 21:58:48 2019 +0200","commit_date":"Mon Apr 8 21:58:48 2019 +0200","message":"Fixed targets for Makefile"},"last_commit":{"short_sha":"3dbb591","long_sha":"3dbb591bcec8224b2400f3ba4b247c448c8a9c5d","author_name":"Jonathan Prieto-Cubides","author_email":"jcu043@uib.no","author_date":"Thu Jun 20 17:24:21 2019 +0200","commit_date":"Thu Jun 20 17:24:21 2019 +0200","message":"Add more theorems"}},"EquivalenceType.tex":{"authors":[{"commits":5,"name":"Jonathan Prieto-Cubides","email":"jcu043@uib.no"}],"total_commits":5,"total_additions":322,"total_subtractions":184,"first_commit":{"short_sha":"bddced8","long_sha":"bddced8b62924abdef08b8978500b0b1e124c58e","author_name":"Jonathan Prieto-Cubides","author_email":"jcu043@uib.no","author_date":"Tue Apr 30 12:24:41 2019 +0200","commit_date":"Tue Apr 30 12:24:41 2019 +0200","message":"Added some lemmas about propositions"},"last_commit":{"short_sha":"3dbb591","long_sha":"3dbb591bcec8224b2400f3ba4b247c448c8a9c5d","author_name":"Jonathan Prieto-Cubides","author_email":"jcu043@uib.no","author_date":"Thu Jun 20 17:24:21 2019 +0200","commit_date":"Thu Jun 20 17:24:21 2019 +0200","message":"Add more theorems"}},"EquivalencesForSets.md":{"authors":[{"commits":4,"name":"Jonathan Prieto-Cubides","email":"jcu043@uib.no"}],"total_commits":4,"total_additions":115,"total_subtractions":50,"first_commit":{"short_sha":"45a20e6","long_sha":"45a20e62531a791d9c0ac12f71570d9c6f79147a","author_name":"Jonathan Prieto-Cubides","author_email":"jcu043@uib.no","author_date":"Wed May 1 02:28:12 2019 +0200","commit_date":"Wed May 1 02:28:12 2019 +0200","message":"Added more lemmas to be proved later"},"last_commit":{"short_sha":"3dbb591","long_sha":"3dbb591bcec8224b2400f3ba4b247c448c8a9c5d","author_name":"Jonathan Prieto-Cubides","author_email":"jcu043@uib.no","author_date":"Thu Jun 20 17:24:21 2019 +0200","commit_date":"Thu Jun 20 17:24:21 2019 +0200","message":"Add more theorems"}},"EquivalencesForSets.tex":null,"FiberType.tex":{"authors":[{"commits":3,"name":"Jonathan Prieto-Cubides","email":"jcu043@uib.no"}],"total_commits":3,"total_additions":100,"total_subtractions":29,"first_commit":{"short_sha":"bddced8","long_sha":"bddced8b62924abdef08b8978500b0b1e124c58e","author_name":"Jonathan Prieto-Cubides","author_email":"jcu043@uib.no","author_date":"Tue Apr 30 12:24:41 2019 +0200","commit_date":"Tue Apr 30 12:24:41 2019 +0200","message":"Added some lemmas about propositions"},"last_commit":{"short_sha":"3dbb591","long_sha":"3dbb591bcec8224b2400f3ba4b247c448c8a9c5d","author_name":"Jonathan Prieto-Cubides","author_email":"jcu043@uib.no","author_date":"Thu Jun 20 17:24:21 2019 +0200","commit_date":"Thu Jun 20 17:24:21 2019 +0200","message":"Add more theorems"}},"FunExtAxiom.md":{"authors":[{"commits":2,"name":"Jonathan Prieto-Cubides","email":"jcu043@uib.no"}],"total_commits":2,"total_additions":111,"total_subtractions":27,"first_commit":{"short_sha":"1da8e9a","long_sha":"1da8e9a76da455368ce8e88f938d457428dcc0b4","author_name":"Jonathan Prieto-Cubides","author_email":"jcu043@uib.no","author_date":"Mon Apr 8 21:58:48 2019 +0200","commit_date":"Mon Apr 8 21:58:48 2019 +0200","message":"Fixed targets for Makefile"},"last_commit":{"short_sha":"e5ca005","long_sha":"e5ca0055367c20b9201e4ff56af1db0d5a7153e3","author_name":"Jonathan Prieto-Cubides","author_email":"jcu043@uib.no","author_date":"Thu Jun 20 03:17:26 2019 +0200","commit_date":"Thu Jun 20 03:17:26 2019 +0200","message":"Tons of additions."}},"FunExtAxiom.tex":{"authors":[{"commits":4,"name":"Jonathan Prieto-Cubides","email":"jcu043@uib.no"}],"total_commits":4,"total_additions":133,"total_subtractions":49,"first_commit":{"short_sha":"bddced8","long_sha":"bddced8b62924abdef08b8978500b0b1e124c58e","author_name":"Jonathan Prieto-Cubides","author_email":"jcu043@uib.no","author_date":"Tue Apr 30 12:24:41 2019 +0200","commit_date":"Tue Apr 30 12:24:41 2019 +0200","message":"Added some lemmas about propositions"},"last_commit":{"short_sha":"3dbb591","long_sha":"3dbb591bcec8224b2400f3ba4b247c448c8a9c5d","author_name":"Jonathan Prieto-Cubides","author_email":"jcu043@uib.no","author_date":"Thu Jun 20 17:24:21 2019 +0200","commit_date":"Thu Jun 20 17:24:21 2019 +0200","message":"Add more theorems"}},"FunExtTransport.md":{"authors":[{"commits":2,"name":"Jonathan Prieto-Cubides","email":"jcu043@uib.no"}],"total_commits":2,"total_additions":89,"total_subtractions":25,"first_commit":{"short_sha":"1da8e9a","long_sha":"1da8e9a76da455368ce8e88f938d457428dcc0b4","author_name":"Jonathan Prieto-Cubides","author_email":"jcu043@uib.no","author_date":"Mon Apr 8 21:58:48 2019 +0200","commit_date":"Mon Apr 8 21:58:48 2019 +0200","message":"Fixed targets for Makefile"},"last_commit":{"short_sha":"e5ca005","long_sha":"e5ca0055367c20b9201e4ff56af1db0d5a7153e3","author_name":"Jonathan Prieto-Cubides","author_email":"jcu043@uib.no","author_date":"Thu Jun 20 03:17:26 2019 +0200","commit_date":"Thu Jun 20 03:17:26 2019 +0200","message":"Tons of additions."}},"FunExtTransport.tex":{"authors":[{"commits":4,"name":"Jonathan Prieto-Cubides","email":"jcu043@uib.no"}],"total_commits":4,"total_additions":105,"total_subtractions":41,"first_commit":{"short_sha":"bddced8","long_sha":"bddced8b62924abdef08b8978500b0b1e124c58e","author_name":"Jonathan Prieto-Cubides","author_email":"jcu043@uib.no","author_date":"Tue Apr 30 12:24:41 2019 +0200","commit_date":"Tue Apr 30 12:24:41 2019 +0200","message":"Added some lemmas about propositions"},"last_commit":{"short_sha":"3dbb591","long_sha":"3dbb591bcec8224b2400f3ba4b247c448c8a9c5d","author_name":"Jonathan Prieto-Cubides","author_email":"jcu043@uib.no","author_date":"Thu Jun 20 17:24:21 2019 +0200","commit_date":"Thu Jun 20 17:24:21 2019 +0200","message":"Add more theorems"}},"FunExtTransportDependent.md":{"authors":[{"commits":2,"name":"Jonathan Prieto-Cubides","email":"jcu043@uib.no"}],"total_commits":2,"total_additions":175,"total_subtractions":69,"first_commit":{"short_sha":"1da8e9a","long_sha":"1da8e9a76da455368ce8e88f938d457428dcc0b4","author_name":"Jonathan Prieto-Cubides","author_email":"jcu043@uib.no","author_date":"Mon Apr 8 21:58:48 2019 +0200","commit_date":"Mon Apr 8 21:58:48 2019 +0200","message":"Fixed targets for Makefile"},"last_commit":{"short_sha":"e5ca005","long_sha":"e5ca0055367c20b9201e4ff56af1db0d5a7153e3","author_name":"Jonathan Prieto-Cubides","author_email":"jcu043@uib.no","author_date":"Thu Jun 20 03:17:26 2019 +0200","commit_date":"Thu Jun 20 03:17:26 2019 +0200","message":"Tons of additions."}},"FunExtTransportDependent.tex":{"authors":[{"commits":3,"name":"Jonathan Prieto-Cubides","email":"jcu043@uib.no"}],"total_commits":3,"total_additions":203,"total_subtractions":97,"first_commit":{"short_sha":"bddced8","long_sha":"bddced8b62924abdef08b8978500b0b1e124c58e","author_name":"Jonathan Prieto-Cubides","author_email":"jcu043@uib.no","author_date":"Tue Apr 30 12:24:41 2019 +0200","commit_date":"Tue Apr 30 12:24:41 2019 +0200","message":"Added some lemmas about propositions"},"last_commit":{"short_sha":"3dbb591","long_sha":"3dbb591bcec8224b2400f3ba4b247c448c8a9c5d","author_name":"Jonathan Prieto-Cubides","author_email":"jcu043@uib.no","author_date":"Thu Jun 20 17:24:21 2019 +0200","commit_date":"Thu Jun 20 17:24:21 2019 +0200","message":"Add more theorems"}},"FundamentalGroupType.md":{"authors":[{"commits":3,"name":"Jonathan Prieto-Cubides","email":"jcu043@uib.no"}],"total_commits":3,"total_additions":79,"total_subtractions":22,"first_commit":{"short_sha":"1da8e9a","long_sha":"1da8e9a76da455368ce8e88f938d457428dcc0b4","author_name":"Jonathan Prieto-Cubides","author_email":"jcu043@uib.no","author_date":"Mon Apr 8 21:58:48 2019 +0200","commit_date":"Mon Apr 8 21:58:48 2019 +0200","message":"Fixed targets for Makefile"},"last_commit":{"short_sha":"e5ca005","long_sha":"e5ca0055367c20b9201e4ff56af1db0d5a7153e3","author_name":"Jonathan Prieto-Cubides","author_email":"jcu043@uib.no","author_date":"Thu Jun 20 03:17:26 2019 +0200","commit_date":"Thu Jun 20 03:17:26 2019 +0200","message":"Tons of additions."}},"FundamentalGroupType.tex":{"authors":[{"commits":3,"name":"Jonathan Prieto-Cubides","email":"jcu043@uib.no"}],"total_commits":3,"total_additions":89,"total_subtractions":32,"first_commit":{"short_sha":"bddced8","long_sha":"bddced8b62924abdef08b8978500b0b1e124c58e","author_name":"Jonathan Prieto-Cubides","author_email":"jcu043@uib.no","author_date":"Tue Apr 30 12:24:41 2019 +0200","commit_date":"Tue Apr 30 12:24:41 2019 +0200","message":"Added some lemmas about propositions"},"last_commit":{"short_sha":"3dbb591","long_sha":"3dbb591bcec8224b2400f3ba4b247c448c8a9c5d","author_name":"Jonathan Prieto-Cubides","author_email":"jcu043@uib.no","author_date":"Thu Jun 20 17:24:21 2019 +0200","commit_date":"Thu Jun 20 17:24:21 2019 +0200","message":"Add more theorems"}},"GroupType.md":{"authors":[{"commits":2,"name":"Jonathan Prieto-Cubides","email":"jcu043@uib.no"}],"total_commits":2,"total_additions":58,"total_subtractions":8,"first_commit":{"short_sha":"1da8e9a","long_sha":"1da8e9a76da455368ce8e88f938d457428dcc0b4","author_name":"Jonathan Prieto-Cubides","author_email":"jcu043@uib.no","author_date":"Mon Apr 8 21:58:48 2019 +0200","commit_date":"Mon Apr 8 21:58:48 2019 +0200","message":"Fixed targets for Makefile"},"last_commit":{"short_sha":"e5ca005","long_sha":"e5ca0055367c20b9201e4ff56af1db0d5a7153e3","author_name":"Jonathan Prieto-Cubides","author_email":"jcu043@uib.no","author_date":"Thu Jun 20 03:17:26 2019 +0200","commit_date":"Thu Jun 20 03:17:26 2019 +0200","message":"Tons of additions."}},"GroupType.tex":{"authors":[{"commits":3,"name":"Jonathan Prieto-Cubides","email":"jcu043@uib.no"}],"total_commits":3,"total_additions":66,"total_subtractions":16,"first_commit":{"short_sha":"bddced8","long_sha":"bddced8b62924abdef08b8978500b0b1e124c58e","author_name":"Jonathan Prieto-Cubides","author_email":"jcu043@uib.no","author_date":"Tue Apr 30 12:24:41 2019 +0200","commit_date":"Tue Apr 30 12:24:41 2019 +0200","message":"Added some lemmas about propositions"},"last_commit":{"short_sha":"3dbb591","long_sha":"3dbb591bcec8224b2400f3ba4b247c448c8a9c5d","author_name":"Jonathan Prieto-Cubides","author_email":"jcu043@uib.no","author_date":"Thu Jun 20 17:24:21 2019 +0200","commit_date":"Thu Jun 20 17:24:21 2019 +0200","message":"Add more theorems"}},"HLevelLemmas.md":{"authors":[{"commits":5,"name":"Jonathan Prieto-Cubides","email":"jcu043@uib.no"}],"total_commits":5,"total_additions":1282,"total_subtractions":855,"first_commit":{"short_sha":"1da8e9a","long_sha":"1da8e9a76da455368ce8e88f938d457428dcc0b4","author_name":"Jonathan Prieto-Cubides","author_email":"jcu043@uib.no","author_date":"Mon Apr 8 21:58:48 2019 +0200","commit_date":"Mon Apr 8 21:58:48 2019 +0200","message":"Fixed targets for Makefile"},"last_commit":{"short_sha":"3dbb591","long_sha":"3dbb591bcec8224b2400f3ba4b247c448c8a9c5d","author_name":"Jonathan Prieto-Cubides","author_email":"jcu043@uib.no","author_date":"Thu Jun 20 17:24:21 2019 +0200","commit_date":"Thu Jun 20 17:24:21 2019 +0200","message":"Add more theorems"}},"HLevelTypes.md":{"authors":[{"commits":4,"name":"Jonathan Prieto-Cubides","email":"jcu043@uib.no"}],"total_commits":4,"total_additions":176,"total_subtractions":49,"first_commit":{"short_sha":"1da8e9a","long_sha":"1da8e9a76da455368ce8e88f938d457428dcc0b4","author_name":"Jonathan Prieto-Cubides","author_email":"jcu043@uib.no","author_date":"Mon Apr 8 21:58:48 2019 +0200","commit_date":"Mon Apr 8 21:58:48 2019 +0200","message":"Fixed targets for Makefile"},"last_commit":{"short_sha":"3dbb591","long_sha":"3dbb591bcec8224b2400f3ba4b247c448c8a9c5d","author_name":"Jonathan Prieto-Cubides","author_email":"jcu043@uib.no","author_date":"Thu Jun 20 17:24:21 2019 +0200","commit_date":"Thu Jun 20 17:24:21 2019 +0200","message":"Add more theorems"}},"HalfAdjointType.md":{"authors":[{"commits":5,"name":"Jonathan Prieto-Cubides","email":"jcu043@uib.no"}],"total_commits":5,"total_additions":261,"total_subtractions":157,"first_commit":{"short_sha":"1da8e9a","long_sha":"1da8e9a76da455368ce8e88f938d457428dcc0b4","author_name":"Jonathan Prieto-Cubides","author_email":"jcu043@uib.no","author_date":"Mon Apr 8 21:58:48 2019 +0200","commit_date":"Mon Apr 8 21:58:48 2019 +0200","message":"Fixed targets for Makefile"},"last_commit":{"short_sha":"3dbb591","long_sha":"3dbb591bcec8224b2400f3ba4b247c448c8a9c5d","author_name":"Jonathan Prieto-Cubides","author_email":"jcu043@uib.no","author_date":"Thu Jun 20 17:24:21 2019 +0200","commit_date":"Thu Jun 20 17:24:21 2019 +0200","message":"Add more theorems"}},"HalfAdjointType.tex":{"authors":[{"commits":3,"name":"Jonathan Prieto-Cubides","email":"jcu043@uib.no"}],"total_commits":3,"total_additions":230,"total_subtractions":126,"first_commit":{"short_sha":"839a04a","long_sha":"839a04abcd6e9b0de087f5c9918c88d149d9fc9f","author_name":"Jonathan Prieto-Cubides","author_email":"jcu043@uib.no","author_date":"Wed May 8 01:26:53 2019 +0200","commit_date":"Wed May 8 01:26:53 2019 +0200","message":"Removed layout information from all post"},"last_commit":{"short_sha":"3dbb591","long_sha":"3dbb591bcec8224b2400f3ba4b247c448c8a9c5d","author_name":"Jonathan Prieto-Cubides","author_email":"jcu043@uib.no","author_date":"Thu Jun 20 17:24:21 2019 +0200","commit_date":"Thu Jun 20 17:24:21 2019 +0200","message":"Add more theorems"}},"HedbergLemmas.md":{"authors":[{"commits":3,"name":"Jonathan Prieto-Cubides","email":"jcu043@uib.no"}],"total_commits":3,"total_additions":104,"total_subtractions":30,"first_commit":{"short_sha":"1da8e9a","long_sha":"1da8e9a76da455368ce8e88f938d457428dcc0b4","author_name":"Jonathan Prieto-Cubides","author_email":"jcu043@uib.no","author_date":"Mon Apr 8 21:58:48 2019 +0200","commit_date":"Mon Apr 8 21:58:48 2019 +0200","message":"Fixed targets for Makefile"},"last_commit":{"short_sha":"e5ca005","long_sha":"e5ca0055367c20b9201e4ff56af1db0d5a7153e3","author_name":"Jonathan Prieto-Cubides","author_email":"jcu043@uib.no","author_date":"Thu Jun 20 03:17:26 2019 +0200","commit_date":"Thu Jun 20 03:17:26 2019 +0200","message":"Tons of additions."}},"HedbergLemmas.tex":{"authors":[{"commits":5,"name":"Jonathan Prieto-Cubides","email":"jcu043@uib.no"}],"total_commits":5,"total_additions":127,"total_subtractions":53,"first_commit":{"short_sha":"bddced8","long_sha":"bddced8b62924abdef08b8978500b0b1e124c58e","author_name":"Jonathan Prieto-Cubides","author_email":"jcu043@uib.no","author_date":"Tue Apr 30 12:24:41 2019 +0200","commit_date":"Tue Apr 30 12:24:41 2019 +0200","message":"Added some lemmas about propositions"},"last_commit":{"short_sha":"3dbb591","long_sha":"3dbb591bcec8224b2400f3ba4b247c448c8a9c5d","author_name":"Jonathan Prieto-Cubides","author_email":"jcu043@uib.no","author_date":"Thu Jun 20 17:24:21 2019 +0200","commit_date":"Thu Jun 20 17:24:21 2019 +0200","message":"Add more theorems"}},"HomotopyLemmas.md":{"authors":[{"commits":4,"name":"Jonathan Prieto-Cubides","email":"jcu043@uib.no"}],"total_commits":4,"total_additions":180,"total_subtractions":63,"first_commit":{"short_sha":"1da8e9a","long_sha":"1da8e9a76da455368ce8e88f938d457428dcc0b4","author_name":"Jonathan Prieto-Cubides","author_email":"jcu043@uib.no","author_date":"Mon Apr 8 21:58:48 2019 +0200","commit_date":"Mon Apr 8 21:58:48 2019 +0200","message":"Fixed targets for Makefile"},"last_commit":{"short_sha":"3dbb591","long_sha":"3dbb591bcec8224b2400f3ba4b247c448c8a9c5d","author_name":"Jonathan Prieto-Cubides","author_email":"jcu043@uib.no","author_date":"Thu Jun 20 17:24:21 2019 +0200","commit_date":"Thu Jun 20 17:24:21 2019 +0200","message":"Add more theorems"}},"HomotopyLemmas.tex":{"authors":[{"commits":3,"name":"Jonathan Prieto-Cubides","email":"jcu043@uib.no"}],"total_commits":3,"total_additions":168,"total_subtractions":51,"first_commit":{"short_sha":"839a04a","long_sha":"839a04abcd6e9b0de087f5c9918c88d149d9fc9f","author_name":"Jonathan Prieto-Cubides","author_email":"jcu043@uib.no","author_date":"Wed May 8 01:26:53 2019 +0200","commit_date":"Wed May 8 01:26:53 2019 +0200","message":"Removed layout information from all post"},"last_commit":{"short_sha":"3dbb591","long_sha":"3dbb591bcec8224b2400f3ba4b247c448c8a9c5d","author_name":"Jonathan Prieto-Cubides","author_email":"jcu043@uib.no","author_date":"Thu Jun 20 17:24:21 2019 +0200","commit_date":"Thu Jun 20 17:24:21 2019 +0200","message":"Add more theorems"}},"HomotopyType.md":{"authors":[{"commits":2,"name":"Jonathan Prieto-Cubides","email":"jcu043@uib.no"}],"total_commits":2,"total_additions":118,"total_subtractions":12,"first_commit":{"short_sha":"1da8e9a","long_sha":"1da8e9a76da455368ce8e88f938d457428dcc0b4","author_name":"Jonathan Prieto-Cubides","author_email":"jcu043@uib.no","author_date":"Mon Apr 8 21:58:48 2019 +0200","commit_date":"Mon Apr 8 21:58:48 2019 +0200","message":"Fixed targets for Makefile"},"last_commit":{"short_sha":"e5ca005","long_sha":"e5ca0055367c20b9201e4ff56af1db0d5a7153e3","author_name":"Jonathan Prieto-Cubides","author_email":"jcu043@uib.no","author_date":"Thu Jun 20 03:17:26 2019 +0200","commit_date":"Thu Jun 20 03:17:26 2019 +0200","message":"Tons of additions."}},"HomotopyType.tex":null,"IntegerType.md":{"authors":[{"commits":3,"name":"Jonathan Prieto-Cubides","email":"jcu043@uib.no"}],"total_commits":3,"total_additions":379,"total_subtractions":174,"first_commit":{"short_sha":"1da8e9a","long_sha":"1da8e9a76da455368ce8e88f938d457428dcc0b4","author_name":"Jonathan Prieto-Cubides","author_email":"jcu043@uib.no","author_date":"Mon Apr 8 21:58:48 2019 +0200","commit_date":"Mon Apr 8 21:58:48 2019 +0200","message":"Fixed targets for Makefile"},"last_commit":{"short_sha":"e5ca005","long_sha":"e5ca0055367c20b9201e4ff56af1db0d5a7153e3","author_name":"Jonathan Prieto-Cubides","author_email":"jcu043@uib.no","author_date":"Thu Jun 20 03:17:26 2019 +0200","commit_date":"Thu Jun 20 03:17:26 2019 +0200","message":"Tons of additions."}},"IntegerType.tex":{"authors":[{"commits":3,"name":"Jonathan Prieto-Cubides","email":"jcu043@uib.no"}],"total_commits":3,"total_additions":439,"total_subtractions":234,"first_commit":{"short_sha":"bddced8","long_sha":"bddced8b62924abdef08b8978500b0b1e124c58e","author_name":"Jonathan Prieto-Cubides","author_email":"jcu043@uib.no","author_date":"Tue Apr 30 12:24:41 2019 +0200","commit_date":"Tue Apr 30 12:24:41 2019 +0200","message":"Added some lemmas about propositions"},"last_commit":{"short_sha":"3dbb591","long_sha":"3dbb591bcec8224b2400f3ba4b247c448c8a9c5d","author_name":"Jonathan Prieto-Cubides","author_email":"jcu043@uib.no","author_date":"Thu Jun 20 17:24:21 2019 +0200","commit_date":"Thu Jun 20 17:24:21 2019 +0200","message":"Add more theorems"}},"IntervalType.md":{"authors":[{"commits":3,"name":"Jonathan Prieto-Cubides","email":"jcu043@uib.no"}],"total_commits":3,"total_additions":80,"total_subtractions":9,"first_commit":{"short_sha":"1da8e9a","long_sha":"1da8e9a76da455368ce8e88f938d457428dcc0b4","author_name":"Jonathan Prieto-Cubides","author_email":"jcu043@uib.no","author_date":"Mon Apr 8 21:58:48 2019 +0200","commit_date":"Mon Apr 8 21:58:48 2019 +0200","message":"Fixed targets for Makefile"},"last_commit":{"short_sha":"e5ca005","long_sha":"e5ca0055367c20b9201e4ff56af1db0d5a7153e3","author_name":"Jonathan Prieto-Cubides","author_email":"jcu043@uib.no","author_date":"Thu Jun 20 03:17:26 2019 +0200","commit_date":"Thu Jun 20 03:17:26 2019 +0200","message":"Tons of additions."}},"IntervalType.tex":{"authors":[{"commits":3,"name":"Jonathan Prieto-Cubides","email":"jcu043@uib.no"}],"total_commits":3,"total_additions":87,"total_subtractions":16,"first_commit":{"short_sha":"bddced8","long_sha":"bddced8b62924abdef08b8978500b0b1e124c58e","author_name":"Jonathan Prieto-Cubides","author_email":"jcu043@uib.no","author_date":"Tue Apr 30 12:24:41 2019 +0200","commit_date":"Tue Apr 30 12:24:41 2019 +0200","message":"Added some lemmas about propositions"},"last_commit":{"short_sha":"3dbb591","long_sha":"3dbb591bcec8224b2400f3ba4b247c448c8a9c5d","author_name":"Jonathan Prieto-Cubides","author_email":"jcu043@uib.no","author_date":"Thu Jun 20 17:24:21 2019 +0200","commit_date":"Thu Jun 20 17:24:21 2019 +0200","message":"Add more theorems"}},"Intro.md":{"authors":[{"commits":4,"name":"Jonathan Prieto-Cubides","email":"jcu043@uib.no"}],"total_commits":4,"total_additions":148,"total_subtractions":53,"first_commit":{"short_sha":"1da8e9a","long_sha":"1da8e9a76da455368ce8e88f938d457428dcc0b4","author_name":"Jonathan Prieto-Cubides","author_email":"jcu043@uib.no","author_date":"Mon Apr 8 21:58:48 2019 +0200","commit_date":"Mon Apr 8 21:58:48 2019 +0200","message":"Fixed targets for Makefile"},"last_commit":{"short_sha":"3dbb591","long_sha":"3dbb591bcec8224b2400f3ba4b247c448c8a9c5d","author_name":"Jonathan Prieto-Cubides","author_email":"jcu043@uib.no","author_date":"Thu Jun 20 17:24:21 2019 +0200","commit_date":"Thu Jun 20 17:24:21 2019 +0200","message":"Add more theorems"}},"MiniHoTT.md":{"authors":[{"commits":4,"name":"Jonathan Prieto-Cubides","email":"jcu043@uib.no"}],"total_commits":4,"total_additions":186,"total_subtractions":93,"first_commit":{"short_sha":"1da8e9a","long_sha":"1da8e9a76da455368ce8e88f938d457428dcc0b4","author_name":"Jonathan Prieto-Cubides","author_email":"jcu043@uib.no","author_date":"Mon Apr 8 21:58:48 2019 +0200","commit_date":"Mon Apr 8 21:58:48 2019 +0200","message":"Fixed targets for Makefile"},"last_commit":{"short_sha":"3dbb591","long_sha":"3dbb591bcec8224b2400f3ba4b247c448c8a9c5d","author_name":"Jonathan Prieto-Cubides","author_email":"jcu043@uib.no","author_date":"Thu Jun 20 17:24:21 2019 +0200","commit_date":"Thu Jun 20 17:24:21 2019 +0200","message":"Add more theorems"}},"MonoidType.md":{"authors":[{"commits":2,"name":"Jonathan Prieto-Cubides","email":"jcu043@uib.no"}],"total_commits":2,"total_additions":47,"total_subtractions":6,"first_commit":{"short_sha":"1da8e9a","long_sha":"1da8e9a76da455368ce8e88f938d457428dcc0b4","author_name":"Jonathan Prieto-Cubides","author_email":"jcu043@uib.no","author_date":"Mon Apr 8 21:58:48 2019 +0200","commit_date":"Mon Apr 8 21:58:48 2019 +0200","message":"Fixed targets for Makefile"},"last_commit":{"short_sha":"e5ca005","long_sha":"e5ca0055367c20b9201e4ff56af1db0d5a7153e3","author_name":"Jonathan Prieto-Cubides","author_email":"jcu043@uib.no","author_date":"Thu Jun 20 03:17:26 2019 +0200","commit_date":"Thu Jun 20 03:17:26 2019 +0200","message":"Tons of additions."}},"MonoidType.tex":{"authors":[{"commits":3,"name":"Jonathan Prieto-Cubides","email":"jcu043@uib.no"}],"total_commits":3,"total_additions":53,"total_subtractions":12,"first_commit":{"short_sha":"839a04a","long_sha":"839a04abcd6e9b0de087f5c9918c88d149d9fc9f","author_name":"Jonathan Prieto-Cubides","author_email":"jcu043@uib.no","author_date":"Wed May 8 01:26:53 2019 +0200","commit_date":"Wed May 8 01:26:53 2019 +0200","message":"Removed layout information from all post"},"last_commit":{"short_sha":"3dbb591","long_sha":"3dbb591bcec8224b2400f3ba4b247c448c8a9c5d","author_name":"Jonathan Prieto-Cubides","author_email":"jcu043@uib.no","author_date":"Thu Jun 20 17:24:21 2019 +0200","commit_date":"Thu Jun 20 17:24:21 2019 +0200","message":"Add more theorems"}},"NaturalType.md":{"authors":[{"commits":4,"name":"Jonathan Prieto-Cubides","email":"jcu043@uib.no"}],"total_commits":4,"total_additions":301,"total_subtractions":163,"first_commit":{"short_sha":"1da8e9a","long_sha":"1da8e9a76da455368ce8e88f938d457428dcc0b4","author_name":"Jonathan Prieto-Cubides","author_email":"jcu043@uib.no","author_date":"Mon Apr 8 21:58:48 2019 +0200","commit_date":"Mon Apr 8 21:58:48 2019 +0200","message":"Fixed targets for Makefile"},"last_commit":{"short_sha":"e5ca005","long_sha":"e5ca0055367c20b9201e4ff56af1db0d5a7153e3","author_name":"Jonathan Prieto-Cubides","author_email":"jcu043@uib.no","author_date":"Thu Jun 20 03:17:26 2019 +0200","commit_date":"Thu Jun 20 03:17:26 2019 +0200","message":"Tons of additions."}},"NaturalType.tex":null,"PiPreserves.md":{"authors":[{"commits":2,"name":"Jonathan Prieto-Cubides","email":"jcu043@uib.no"}],"total_commits":2,"total_additions":114,"total_subtractions":26,"first_commit":{"short_sha":"1da8e9a","long_sha":"1da8e9a76da455368ce8e88f938d457428dcc0b4","author_name":"Jonathan Prieto-Cubides","author_email":"jcu043@uib.no","author_date":"Mon Apr 8 21:58:48 2019 +0200","commit_date":"Mon Apr 8 21:58:48 2019 +0200","message":"Fixed targets for Makefile"},"last_commit":{"short_sha":"e5ca005","long_sha":"e5ca0055367c20b9201e4ff56af1db0d5a7153e3","author_name":"Jonathan Prieto-Cubides","author_email":"jcu043@uib.no","author_date":"Thu Jun 20 03:17:26 2019 +0200","commit_date":"Thu Jun 20 03:17:26 2019 +0200","message":"Tons of additions."}},"PiPreserves.tex":null,"ProductIdentities.md":{"authors":[{"commits":1,"name":"Jonathan Prieto-Cubides","email":"jcu043@uib.no"}],"total_commits":1,"total_additions":97,"total_subtractions":0,"first_commit":{"short_sha":"e5ca005","long_sha":"e5ca0055367c20b9201e4ff56af1db0d5a7153e3","author_name":"Jonathan Prieto-Cubides","author_email":"jcu043@uib.no","author_date":"Thu Jun 20 03:17:26 2019 +0200","commit_date":"Thu Jun 20 03:17:26 2019 +0200","message":"Tons of additions."},"last_commit":{"short_sha":"e5ca005","long_sha":"e5ca0055367c20b9201e4ff56af1db0d5a7153e3","author_name":"Jonathan Prieto-Cubides","author_email":"jcu043@uib.no","author_date":"Thu Jun 20 03:17:26 2019 +0200","commit_date":"Thu Jun 20 03:17:26 2019 +0200","message":"Tons of additions."}},"ProductIdentities.tex":null,"QuasiinverseLemmas.md":{"authors":[{"commits":4,"name":"Jonathan Prieto-Cubides","email":"jcu043@uib.no"}],"total_commits":4,"total_additions":227,"total_subtractions":109,"first_commit":{"short_sha":"1da8e9a","long_sha":"1da8e9a76da455368ce8e88f938d457428dcc0b4","author_name":"Jonathan Prieto-Cubides","author_email":"jcu043@uib.no","author_date":"Mon Apr 8 21:58:48 2019 +0200","commit_date":"Mon Apr 8 21:58:48 2019 +0200","message":"Fixed targets for Makefile"},"last_commit":{"short_sha":"3dbb591","long_sha":"3dbb591bcec8224b2400f3ba4b247c448c8a9c5d","author_name":"Jonathan Prieto-Cubides","author_email":"jcu043@uib.no","author_date":"Thu Jun 20 17:24:21 2019 +0200","commit_date":"Thu Jun 20 17:24:21 2019 +0200","message":"Add more theorems"}},"QuasiinverseLemmas.tex":{"authors":[{"commits":3,"name":"Jonathan Prieto-Cubides","email":"jcu043@uib.no"}],"total_commits":3,"total_additions":202,"total_subtractions":84,"first_commit":{"short_sha":"839a04a","long_sha":"839a04abcd6e9b0de087f5c9918c88d149d9fc9f","author_name":"Jonathan Prieto-Cubides","author_email":"jcu043@uib.no","author_date":"Wed May 8 01:26:53 2019 +0200","commit_date":"Wed May 8 01:26:53 2019 +0200","message":"Removed layout information from all post"},"last_commit":{"short_sha":"3dbb591","long_sha":"3dbb591bcec8224b2400f3ba4b247c448c8a9c5d","author_name":"Jonathan Prieto-Cubides","author_email":"jcu043@uib.no","author_date":"Thu Jun 20 17:24:21 2019 +0200","commit_date":"Thu Jun 20 17:24:21 2019 +0200","message":"Add more theorems"}},"QuasiinverseType.md":{"authors":[{"commits":5,"name":"Jonathan Prieto-Cubides","email":"jcu043@uib.no"}],"total_commits":5,"total_additions":287,"total_subtractions":164,"first_commit":{"short_sha":"1da8e9a","long_sha":"1da8e9a76da455368ce8e88f938d457428dcc0b4","author_name":"Jonathan Prieto-Cubides","author_email":"jcu043@uib.no","author_date":"Mon Apr 8 21:58:48 2019 +0200","commit_date":"Mon Apr 8 21:58:48 2019 +0200","message":"Fixed targets for Makefile"},"last_commit":{"short_sha":"3dbb591","long_sha":"3dbb591bcec8224b2400f3ba4b247c448c8a9c5d","author_name":"Jonathan Prieto-Cubides","author_email":"jcu043@uib.no","author_date":"Thu Jun 20 17:24:21 2019 +0200","commit_date":"Thu Jun 20 17:24:21 2019 +0200","message":"Add more theorems"}},"QuasiinverseType.tex":{"authors":[{"commits":3,"name":"Jonathan Prieto-Cubides","email":"jcu043@uib.no"}],"total_commits":3,"total_additions":272,"total_subtractions":149,"first_commit":{"short_sha":"839a04a","long_sha":"839a04abcd6e9b0de087f5c9918c88d149d9fc9f","author_name":"Jonathan Prieto-Cubides","author_email":"jcu043@uib.no","author_date":"Wed May 8 01:26:53 2019 +0200","commit_date":"Wed May 8 01:26:53 2019 +0200","message":"Removed layout information from all post"},"last_commit":{"short_sha":"3dbb591","long_sha":"3dbb591bcec8224b2400f3ba4b247c448c8a9c5d","author_name":"Jonathan Prieto-Cubides","author_email":"jcu043@uib.no","author_date":"Thu Jun 20 17:24:21 2019 +0200","commit_date":"Thu Jun 20 17:24:21 2019 +0200","message":"Add more theorems"}},"QuotientType.md":{"authors":[{"commits":4,"name":"Jonathan Prieto-Cubides","email":"jcu043@uib.no"}],"total_commits":4,"total_additions":118,"total_subtractions":25,"first_commit":{"short_sha":"1da8e9a","long_sha":"1da8e9a76da455368ce8e88f938d457428dcc0b4","author_name":"Jonathan Prieto-Cubides","author_email":"jcu043@uib.no","author_date":"Mon Apr 8 21:58:48 2019 +0200","commit_date":"Mon Apr 8 21:58:48 2019 +0200","message":"Fixed targets for Makefile"},"last_commit":{"short_sha":"e5ca005","long_sha":"e5ca0055367c20b9201e4ff56af1db0d5a7153e3","author_name":"Jonathan Prieto-Cubides","author_email":"jcu043@uib.no","author_date":"Thu Jun 20 03:17:26 2019 +0200","commit_date":"Thu Jun 20 03:17:26 2019 +0200","message":"Tons of additions."}},"QuotientType.tex":null,"RelationType.md":{"authors":[{"commits":2,"name":"Jonathan Prieto-Cubides","email":"jcu043@uib.no"}],"total_commits":2,"total_additions":37,"total_subtractions":3,"first_commit":{"short_sha":"1da8e9a","long_sha":"1da8e9a76da455368ce8e88f938d457428dcc0b4","author_name":"Jonathan Prieto-Cubides","author_email":"jcu043@uib.no","author_date":"Mon Apr 8 21:58:48 2019 +0200","commit_date":"Mon Apr 8 21:58:48 2019 +0200","message":"Fixed targets for Makefile"},"last_commit":{"short_sha":"e5ca005","long_sha":"e5ca0055367c20b9201e4ff56af1db0d5a7153e3","author_name":"Jonathan Prieto-Cubides","author_email":"jcu043@uib.no","author_date":"Thu Jun 20 03:17:26 2019 +0200","commit_date":"Thu Jun 20 03:17:26 2019 +0200","message":"Tons of additions."}},"RelationType.tex":null,"SetTruncationType.md":{"authors":[{"commits":2,"name":"Jonathan Prieto-Cubides","email":"jcu043@uib.no"}],"total_commits":2,"total_additions":67,"total_subtractions":6,"first_commit":{"short_sha":"1da8e9a","long_sha":"1da8e9a76da455368ce8e88f938d457428dcc0b4","author_name":"Jonathan Prieto-Cubides","author_email":"jcu043@uib.no","author_date":"Mon Apr 8 21:58:48 2019 +0200","commit_date":"Mon Apr 8 21:58:48 2019 +0200","message":"Fixed targets for Makefile"},"last_commit":{"short_sha":"e5ca005","long_sha":"e5ca0055367c20b9201e4ff56af1db0d5a7153e3","author_name":"Jonathan Prieto-Cubides","author_email":"jcu043@uib.no","author_date":"Thu Jun 20 03:17:26 2019 +0200","commit_date":"Thu Jun 20 03:17:26 2019 +0200","message":"Tons of additions."}},"SetTruncationType.tex":null,"SigmaEquivalence.md":{"authors":[{"commits":3,"name":"Jonathan Prieto-Cubides","email":"jcu043@uib.no"}],"total_commits":3,"total_additions":126,"total_subtractions":42,"first_commit":{"short_sha":"1da8e9a","long_sha":"1da8e9a76da455368ce8e88f938d457428dcc0b4","author_name":"Jonathan Prieto-Cubides","author_email":"jcu043@uib.no","author_date":"Mon Apr 8 21:58:48 2019 +0200","commit_date":"Mon Apr 8 21:58:48 2019 +0200","message":"Fixed targets for Makefile"},"last_commit":{"short_sha":"e5ca005","long_sha":"e5ca0055367c20b9201e4ff56af1db0d5a7153e3","author_name":"Jonathan Prieto-Cubides","author_email":"jcu043@uib.no","author_date":"Thu Jun 20 03:17:26 2019 +0200","commit_date":"Thu Jun 20 03:17:26 2019 +0200","message":"Tons of additions."}},"SigmaEquivalence.tex":null,"SigmaPreserves.md":{"authors":[{"commits":3,"name":"Jonathan Prieto-Cubides","email":"jcu043@uib.no"}],"total_commits":3,"total_additions":302,"total_subtractions":123,"first_commit":{"short_sha":"1da8e9a","long_sha":"1da8e9a76da455368ce8e88f938d457428dcc0b4","author_name":"Jonathan Prieto-Cubides","author_email":"jcu043@uib.no","author_date":"Mon Apr 8 21:58:48 2019 +0200","commit_date":"Mon Apr 8 21:58:48 2019 +0200","message":"Fixed targets for Makefile"},"last_commit":{"short_sha":"e5ca005","long_sha":"e5ca0055367c20b9201e4ff56af1db0d5a7153e3","author_name":"Jonathan Prieto-Cubides","author_email":"jcu043@uib.no","author_date":"Thu Jun 20 03:17:26 2019 +0200","commit_date":"Thu Jun 20 03:17:26 2019 +0200","message":"Tons of additions."}},"SigmaPreserves.tex":null,"SuspensionType.md":{"authors":[{"commits":3,"name":"Jonathan Prieto-Cubides","email":"jcu043@uib.no"}],"total_commits":3,"total_additions":114,"total_subtractions":18,"first_commit":{"short_sha":"1da8e9a","long_sha":"1da8e9a76da455368ce8e88f938d457428dcc0b4","author_name":"Jonathan Prieto-Cubides","author_email":"jcu043@uib.no","author_date":"Mon Apr 8 21:58:48 2019 +0200","commit_date":"Mon Apr 8 21:58:48 2019 +0200","message":"Fixed targets for Makefile"},"last_commit":{"short_sha":"e5ca005","long_sha":"e5ca0055367c20b9201e4ff56af1db0d5a7153e3","author_name":"Jonathan Prieto-Cubides","author_email":"jcu043@uib.no","author_date":"Thu Jun 20 03:17:26 2019 +0200","commit_date":"Thu Jun 20 03:17:26 2019 +0200","message":"Tons of additions."}},"SuspensionType.tex":null,"TransportLemmas.md":{"authors":[{"commits":4,"name":"Jonathan Prieto-Cubides","email":"jcu043@uib.no"}],"total_commits":4,"total_additions":990,"total_subtractions":604,"first_commit":{"short_sha":"1da8e9a","long_sha":"1da8e9a76da455368ce8e88f938d457428dcc0b4","author_name":"Jonathan Prieto-Cubides","author_email":"jcu043@uib.no","author_date":"Mon Apr 8 21:58:48 2019 +0200","commit_date":"Mon Apr 8 21:58:48 2019 +0200","message":"Fixed targets for Makefile"},"last_commit":{"short_sha":"3dbb591","long_sha":"3dbb591bcec8224b2400f3ba4b247c448c8a9c5d","author_name":"Jonathan Prieto-Cubides","author_email":"jcu043@uib.no","author_date":"Thu Jun 20 17:24:21 2019 +0200","commit_date":"Thu Jun 20 17:24:21 2019 +0200","message":"Add more theorems"}},"TransportLemmas.tex":null,"TruncationType.md":{"authors":[{"commits":2,"name":"Jonathan Prieto-Cubides","email":"jcu043@uib.no"}],"total_commits":2,"total_additions":66,"total_subtractions":6,"first_commit":{"short_sha":"1da8e9a","long_sha":"1da8e9a76da455368ce8e88f938d457428dcc0b4","author_name":"Jonathan Prieto-Cubides","author_email":"jcu043@uib.no","author_date":"Mon Apr 8 21:58:48 2019 +0200","commit_date":"Mon Apr 8 21:58:48 2019 +0200","message":"Fixed targets for Makefile"},"last_commit":{"short_sha":"e5ca005","long_sha":"e5ca0055367c20b9201e4ff56af1db0d5a7153e3","author_name":"Jonathan Prieto-Cubides","author_email":"jcu043@uib.no","author_date":"Thu Jun 20 03:17:26 2019 +0200","commit_date":"Thu Jun 20 03:17:26 2019 +0200","message":"Tons of additions."}},"TruncationType.tex":null,"UnivalenceAxiom.md":{"authors":[{"commits":3,"name":"Jonathan Prieto-Cubides","email":"jcu043@uib.no"}],"total_commits":3,"total_additions":128,"total_subtractions":17,"first_commit":{"short_sha":"1da8e9a","long_sha":"1da8e9a76da455368ce8e88f938d457428dcc0b4","author_name":"Jonathan Prieto-Cubides","author_email":"jcu043@uib.no","author_date":"Mon Apr 8 21:58:48 2019 +0200","commit_date":"Mon Apr 8 21:58:48 2019 +0200","message":"Fixed targets for Makefile"},"last_commit":{"short_sha":"e5ca005","long_sha":"e5ca0055367c20b9201e4ff56af1db0d5a7153e3","author_name":"Jonathan Prieto-Cubides","author_email":"jcu043@uib.no","author_date":"Thu Jun 20 03:17:26 2019 +0200","commit_date":"Thu Jun 20 03:17:26 2019 +0200","message":"Tons of additions."}},"UnivalenceAxiom.tex":null,"UnivalenceLemmas.md":{"authors":[{"commits":2,"name":"Jonathan Prieto-Cubides","email":"jcu043@uib.no"}],"total_commits":2,"total_additions":134,"total_subtractions":20,"first_commit":{"short_sha":"1da8e9a","long_sha":"1da8e9a76da455368ce8e88f938d457428dcc0b4","author_name":"Jonathan Prieto-Cubides","author_email":"jcu043@uib.no","author_date":"Mon Apr 8 21:58:48 2019 +0200","commit_date":"Mon Apr 8 21:58:48 2019 +0200","message":"Fixed targets for Makefile"},"last_commit":{"short_sha":"e5ca005","long_sha":"e5ca0055367c20b9201e4ff56af1db0d5a7153e3","author_name":"Jonathan Prieto-Cubides","author_email":"jcu043@uib.no","author_date":"Thu Jun 20 03:17:26 2019 +0200","commit_date":"Thu Jun 20 03:17:26 2019 +0200","message":"Tons of additions."}},"UnivalenceTransport.md":{"authors":[{"commits":3,"name":"Jonathan Prieto-Cubides","email":"jcu043@uib.no"}],"total_commits":3,"total_additions":143,"total_subtractions":43,"first_commit":{"short_sha":"1da8e9a","long_sha":"1da8e9a76da455368ce8e88f938d457428dcc0b4","author_name":"Jonathan Prieto-Cubides","author_email":"jcu043@uib.no","author_date":"Mon Apr 8 21:58:48 2019 +0200","commit_date":"Mon Apr 8 21:58:48 2019 +0200","message":"Fixed targets for Makefile"},"last_commit":{"short_sha":"e5ca005","long_sha":"e5ca0055367c20b9201e4ff56af1db0d5a7153e3","author_name":"Jonathan Prieto-Cubides","author_email":"jcu043@uib.no","author_date":"Thu Jun 20 03:17:26 2019 +0200","commit_date":"Thu Jun 20 03:17:26 2019 +0200","message":"Tons of additions."}},"UnivalenceTransport.tex":null,"atom.xml":{"authors":[{"commits":1,"name":"Jonathan Prieto-Cubides","email":"jcu043@uib.no"}],"total_commits":1,"total_additions":28,"total_subtractions":0,"first_commit":{"short_sha":"51a0ec7","long_sha":"51a0ec7cc21422c39e9bc138691d9f9726746854","author_name":"Jonathan Prieto-Cubides","author_email":"jcu043@uib.no","author_date":"Mon Apr 8 18:40:13 2019 +0200","commit_date":"Mon Apr 8 18:40:13 2019 +0200","message":"Fixing html generations for jekyll"},"last_commit":{"short_sha":"51a0ec7","long_sha":"51a0ec7cc21422c39e9bc138691d9f9726746854","author_name":"Jonathan Prieto-Cubides","author_email":"jcu043@uib.no","author_date":"Mon Apr 8 18:40:13 2019 +0200","commit_date":"Mon Apr 8 18:40:13 2019 +0200","message":"Fixing html generations for jekyll"}},"index.md":{"authors":[{"commits":4,"name":"Jonathan Prieto-Cubides","email":"jcu043@uib.no"}],"total_commits":4,"total_additions":295,"total_subtractions":52,"first_commit":{"short_sha":"51a0ec7","long_sha":"51a0ec7cc21422c39e9bc138691d9f9726746854","author_name":"Jonathan Prieto-Cubides","author_email":"jcu043@uib.no","author_date":"Mon Apr 8 18:40:13 2019 +0200","commit_date":"Mon Apr 8 18:40:13 2019 +0200","message":"Fixing html generations for jekyll"},"last_commit":{"short_sha":"3dbb591","long_sha":"3dbb591bcec8224b2400f3ba4b247c448c8a9c5d","author_name":"Jonathan Prieto-Cubides","author_email":"jcu043@uib.no","author_date":"Thu Jun 20 17:24:21 2019 +0200","commit_date":"Thu Jun 20 17:24:21 2019 +0200","message":"Add more theorems"}}}}